genomics_demo/__init__.py
genomics_demo/dna.py
genomics_demo/rna.py
genomics_demo/scripts.py
genomics_demo-0.0.1.dist-info/METADATA
genomics_demo-0.0.1.dist-info/RECORD
genomics_demo-0.0.1.dist-info/WHEEL
genomics_demo-0.0.1.dist-info/entry_points.txt
genomics_demo-0.0.1.dist-info/top_level.txt
