Metadata-Version: 2.1
Name: genomics-demo
Version: 0.0.1
Summary: The best genomics package ever.  Just kidding--do NOT use this!
Home-page: UNKNOWN
Author: Nicholas A. Del Grosso
Author-email: delgrosso.nick@gmail.com
License: MIT
Platform: UNKNOWN
